aelf/__init__.py
aelf/client.py
aelf/toolkits.py
aelf/types_pb2.py
aelf_sdk-1.2.3.dist-info/METADATA
aelf_sdk-1.2.3.dist-info/WHEEL
aelf_sdk-1.2.3.dist-info/top_level.txt
aelf_sdk-1.2.3.dist-info/RECORD
