Metadata-Version: 2.1
Name: aelf-sdk
Version: 1.2.3
Summary: Python SDK for AElf
Home-page: https://github.com/AElf/aelf-sdk.py
Author: UNKNOWN
Author-email: UNKNOWN
License: UNKNOWN
Platform: UNKNOWN
Requires-Dist: requests
Requires-Dist: protobuf
Requires-Dist: base58
Requires-Dist: coincurve
